mbwebapppy/__init__.py
mbwebapppy/controller.py
mbwebapppy-0.1.11.dist-info/METADATA
mbwebapppy-0.1.11.dist-info/RECORD
mbwebapppy-0.1.11.dist-info/WHEEL
mbwebapppy-0.1.11.dist-info/top_level.txt
