Metadata-Version: 2.1
Name: mbwebapppy
Version: 0.1.11
Summary: A library to work with Mercedes WebApp API.
Home-page: UNKNOWN
Author: Rene Nulsch
Author-email: github.mbwebapppy@nulsch.de
License: MIT License
Platform: UNKNOWN
Classifier: Intended Audience :: Developers
Classifier: Operating System :: OS Independent
Classifier: Programming Language :: Python :: 3
Classifier: Programming Language :: Python :: 3.4
Classifier: Programming Language :: Python :: 3.5
Classifier: Programming Language :: Python :: 3.6
Classifier: Programming Language :: Python :: 3.7
Classifier: Topic :: Internet
Requires-Python: >=3
Requires-Dist: requests (>=2.18.4)
Requires-Dist: lxml (>=4.2.0)
